presto_chango/__init__.py
presto_chango/app.py
presto_chango/database.py
presto_chango/song.py
presto_chango/tester.py
Presto_Chango-1.0.2.dist-info/LICENSE
Presto_Chango-1.0.2.dist-info/METADATA
Presto_Chango-1.0.2.dist-info/WHEEL
Presto_Chango-1.0.2.dist-info/entry_points.txt
Presto_Chango-1.0.2.dist-info/top_level.txt
Presto_Chango-1.0.2.dist-info/RECORD
