Metadata-Version: 2.1
Name: Presto-Chango
Version: 1.0.2
Summary: Music identification through audio fingerprinting
Home-page: https://github.com/yashrajkakkad/presto-chango
Author: Prayag Savsani
Author-email: prayag.s@ahduni.edu.in
License: UNKNOWN
Platform: UNKNOWN
Classifier: Development Status :: 4 - Beta
Classifier: Environment :: Console
Classifier: License :: OSI Approved :: MIT License
Classifier: Operating System :: OS Independent
Classifier: Programming Language :: Python :: 3
Classifier: Topic :: Multimedia :: Sound/Audio :: Analysis
Requires-Dist: Click
Requires-Dist: scipy
Requires-Dist: numpy
Requires-Dist: scikit-image
Requires-Dist: matplotlib
Requires-Dist: pydub
Requires-Dist: pyaudio
Requires-Dist: appdirs
